wenyang/__init__.py
wenyang/log.py
wenyang/update_p4client.py
wenyang-1.1.0.dist-info/LICENSE
wenyang-1.1.0.dist-info/METADATA
wenyang-1.1.0.dist-info/WHEEL
wenyang-1.1.0.dist-info/top_level.txt
wenyang-1.1.0.dist-info/RECORD
