Metadata-Version: 2.1
Name: wenyang
Version: 1.1.0
Summary: A utility package
Home-page: https://github.com/eecsmap/wenyang
Author: Wenyang Duan
Author-email: wenyang.duan@gmail.com
Classifier: Programming Language :: Python :: 3
Classifier: License :: OSI Approved :: MIT License
Classifier: Operating System :: OS Independent
Requires-Python: >=3.6
License-File: LICENSE
